EMDT/__init__.py
EMDT/emdt.py
EMDT/extraction.py
EMDT/mining.py
EMDT/util.py
EMDT-0.2.0.dist-info/DESCRIPTION.rst
EMDT-0.2.0.dist-info/METADATA
EMDT-0.2.0.dist-info/RECORD
EMDT-0.2.0.dist-info/WHEEL
EMDT-0.2.0.dist-info/metadata.json
EMDT-0.2.0.dist-info/top_level.txt
