Metadata-Version: 2.0
Name: EMDT
Version: 0.2.0
Summary: EMDT,Extraction and Mining Algorithm for Question Answering Pair Based on Web Document Density and Tags
Home-page: https://github.com/pzs741/EMDT
Author: Ex_treme
Author-email: pzsyjsgldd@163.com
License: MIT
Platform: UNKNOWN
Classifier: Programming Language :: Python :: 3
Classifier: Natural Language :: English
Classifier: Intended Audience :: Developers
Requires-Dist: TEDT (>=0.5)
Requires-Dist: beautifulsoup4 (==4.5.3)
Requires-Dist: jieba (>=0.39)
Requires-Dist: requests (>=2.18.4)
